shudaodao_core/__init__.py
shudaodao_core/app/base_app.cpython-310-x86_64-linux-gnu.so
shudaodao_core/app/base_app.pyi
shudaodao_core/app/base_context.cpython-310-x86_64-linux-gnu.so
shudaodao_core/app/base_context.pyi
shudaodao_core/auth/auth_data_rule.cpython-310-x86_64-linux-gnu.so
shudaodao_core/auth/auth_data_rule.pyi
shudaodao_core/auth/auth_router.cpython-310-x86_64-linux-gnu.so
shudaodao_core/auth/auth_router.pyi
shudaodao_core/config/app_config.cpython-310-x86_64-linux-gnu.so
shudaodao_core/config/app_config.pyi
shudaodao_core/config/loader.cpython-310-x86_64-linux-gnu.so
shudaodao_core/config/loader.pyi
shudaodao_core/config/running_config.cpython-310-x86_64-linux-gnu.so
shudaodao_core/config/running_config.pyi
shudaodao_core/config/schemas/app_config.py
shudaodao_core/config/schemas/auth.py
shudaodao_core/config/schemas/context.py
shudaodao_core/config/schemas/models.py
shudaodao_core/config/schemas/routers.py
shudaodao_core/config/schemas/snowflake.py
shudaodao_core/config/schemas/storage.py
shudaodao_core/config/schemas/webapp.py
shudaodao_core/controller/generic_controller.py
shudaodao_core/controller/router_config.py
shudaodao_core/controller/table_controller.py
shudaodao_core/engine/casbin_engine.cpython-310-x86_64-linux-gnu.so
shudaodao_core/engine/casbin_engine.pyi
shudaodao_core/engine/database_engine.cpython-310-x86_64-linux-gnu.so
shudaodao_core/engine/database_engine.pyi
shudaodao_core/engine/disk_engine.cpython-310-x86_64-linux-gnu.so
shudaodao_core/engine/disk_engine.pyi
shudaodao_core/engine/redis_engine.cpython-310-x86_64-linux-gnu.so
shudaodao_core/engine/redis_engine.pyi
shudaodao_core/enum/label_enum.cpython-310-x86_64-linux-gnu.so
shudaodao_core/enum/label_enum.pyi
shudaodao_core/enum/resolve_enum.cpython-310-x86_64-linux-gnu.so
shudaodao_core/enum/resolve_enum.pyi
shudaodao_core/exception/format_valid_error.cpython-310-x86_64-linux-gnu.so
shudaodao_core/exception/format_valid_error.pyi
shudaodao-0.1.48.dist-info/METADATA
shudaodao-0.1.48.dist-info/WHEEL
shudaodao-0.1.48.dist-info/top_level.txt
shudaodao-0.1.48.dist-info/RECORD
shudaodao-0.1.48.dist-info/licenses/LICENSE
