Metadata-Version: 2.4
Name: shudaodao
Version: 0.1.48
Summary: SmartShudao
Author-email: SmartShudao <lf_shao@163.com>
License-Expression: MIT
Requires-Python: >=3.10
License-File: LICENSE
Requires-Dist: aiosqlite>=0.21.0
Requires-Dist: asyncpg>=0.30.0
Requires-Dist: bcrypt>=5.0.0
Requires-Dist: casbin>=1.43.0
Requires-Dist: casbin-async-sqlalchemy-adapter>=1.10.0
Requires-Dist: fastapi>=0.117.1
Requires-Dist: greenlet>=3.2.4
Requires-Dist: jinja2>=3.1.6
Requires-Dist: psycopg2-binary>=2.9.10
Requires-Dist: pydantic[email]>=2.11.7
Requires-Dist: pyjwt[crypto]>=2.10.1
Requires-Dist: python-multipart>=0.0.20
Requires-Dist: pyyaml>=6.0.2
Requires-Dist: redis>=6.4.0
Requires-Dist: sqlmodel>=0.0.25
Dynamic: license-file
